simpli/__init__.py
simpli/default_tasks.json
simpli/default_tasks.py
simpli/manager.py
simpli/nbpackage_tasks.json
simpli/nbpackage_tasks.py
simpli/startup.py
simpli/support.py
simpli/static/main.js
simpli/static/resources/_material.css.map
simpli/static/resources/_material.scss
simpli/static/resources/taskList.js
simpli/static/resources/taskWidget.js
simpli/static/resources/theme.css
simpli/static/resources/theme.css.map
simpli/static/resources/theme.scss
simpli-1.0.0b2.dist-info/DESCRIPTION.rst
simpli-1.0.0b2.dist-info/METADATA
simpli-1.0.0b2.dist-info/RECORD
simpli-1.0.0b2.dist-info/WHEEL
simpli-1.0.0b2.dist-info/metadata.json
simpli-1.0.0b2.dist-info/top_level.txt
