Metadata-Version: 2.0
Name: simpli
Version: 1.0.0b2
Summary: A simple execution interface for Jupyter Notebook.
Home-page: https://github.com/ucsd-ccal/simpli
Author: Clarence Mah
Author-email: ckmah@ucsd.edu
License: UNKNOWN
Download-URL: https://github.com/ucsd-ccal/simpli
Keywords: bioinformatics biology development interface widget
Platform: UNKNOWN
Classifier: Development Status :: 4 - Beta
Classifier: License :: OSI Approved :: MIT License
Classifier: Programming Language :: Python :: 3.5
Requires-Dist: ipywidgets (>=5.2.0)
Requires-Dist: jupyter
Requires-Dist: jupyter-declarativewidgets (>=0.7.0)
Requires-Dist: notebook (>=4.2.0)
